eisenberg/__init__.py
eisenberg-0.0.4.dist-info/METADATA
eisenberg-0.0.4.dist-info/WHEEL
eisenberg-0.0.4.dist-info/top_level.txt
eisenberg-0.0.4.dist-info/RECORD
