Metadata-Version: 2.1
Name: eisenberg
Version: 0.0.4
Summary: UNKNOWN
Author: eisenberg
Author-email: eisenberg@test.com
License: UNKNOWN
Platform: UNKNOWN
Requires-Dist: Werkzeug (>=2.2.0a1)
Requires-Dist: Jinja2 (>=3.0)
Requires-Dist: itsdangerous (>=2.0)
Requires-Dist: click (>=8.0)
Requires-Dist: importlib-metadata (>=3.6.0) ; python_version < "3.10"
Provides-Extra: async
Requires-Dist: asgiref (>=3.2) ; extra == 'async'
Provides-Extra: dotenv
Requires-Dist: python-dotenv ; extra == 'dotenv'
